NL_UTILS/DIRECTORY.py
NL_UTILS/DIRECTORY_TESTS.py
NL_UTILS/FILE.py
NL_UTILS/FILESYSTEM.py
NL_UTILS/FILESYSTEM_OBJECT.py
NL_UTILS/FILESYSTEM_TESTS.py
NL_UTILS/FILE_TESTS.py
NL_UTILS/HANDLER.py
NL_UTILS/HANDLER_MOCKS.py
NL_UTILS/HANDLER_TESTS.py
NL_UTILS/IMPORTS.py
NL_UTILS/LOG.py
NL_UTILS/LOG_BUFFER.py
NL_UTILS/LOG_BUFFER_INFO.py
NL_UTILS/LOG_BUFFER_TEST.py
NL_UTILS/LOG_EXCEPTION.py
NL_UTILS/LOG_EXCLUDES.py
NL_UTILS/LOG_PARALLEL.py
NL_UTILS/LOG_PLACEHOLDER.py
NL_UTILS/LOG_SETTINGS.py
NL_UTILS/LOG_TESTS.py
NL_UTILS/PRINTABLE.py
NL_UTILS/PRINTABLE_DICT.py
NL_UTILS/PROFILER.py
NL_UTILS/PYTHON_APP.py
NL_UTILS/PYTHON_CLASS.py
NL_UTILS/PYTHON_CLASS_TESTS.py
NL_UTILS/PYTHON_EDITOR.py
NL_UTILS/PYTHON_EDITOR_TEST.py
NL_UTILS/PYTHON_METHOD.py
NL_UTILS/PYTHON_METHOD_TESTS.py
NL_UTILS/RUNNER.py
NL_UTILS/SETTINGS.py
NL_UTILS/STDOUT.py
NL_UTILS/STDOUT_TEST.py
NL_UTILS/STRUCT.py
NL_UTILS/STRUCT_ATTRIBUTES.py
NL_UTILS/STRUCT_BASE.py
NL_UTILS/STRUCT_CONVERT.py
NL_UTILS/STRUCT_DICTIONARIES.py
NL_UTILS/STRUCT_LISTS.py
NL_UTILS/STRUCT_TESTS.py
NL_UTILS/TESTS.py
NL_UTILS/TESTS_TESTS.py
NL_UTILS/TEST_UTILS.py
NL_UTILS/TIMER.py
NL_UTILS/UTILS.py
NL_UTILS/UTILS_CACHE.py
NL_UTILS/UTILS_CRYPTOGRAPHY.py
NL_UTILS/UTILS_LISTS.py
NL_UTILS/UTILS_LISTS_TESTS.py
NL_UTILS/UTILS_OBJECTS.py
NL_UTILS/UTILS_OBJECTS_TESTS.py
NL_UTILS/UTILS_OS.py
NL_UTILS/UTILS_OS_TESTS.py
NL_UTILS/UTILS_PYTHON.py
NL_UTILS/UTILS_PYTHON_TESTS.py
NL_UTILS/UTILS_TESTS.py
NL_UTILS/UTILS_TIME.py
NL_UTILS/UTILS_TIME_TESTS.py
NL_UTILS/UTILS_TYPES.py
NL_UTILS/UTILS_TYPES_TESTS.py
NL_UTILS/UTILS_YAML.py
NL_UTILS/UTILS_YAML_TESTS.py
NL_UTILS/UUID.py
NL_UTILS/WEB_BASE.py
NL_UTILS/ZIP.py
NL_UTILS/ZIP_FILE.py
NL_UTILS/ZIP_INFO.py
NL_UTILS/__init__.py
NL_UTILS/common.py
NL_UTILS/deploy.py
NL_UTILS/hello.py
NL_UTILS/imports.json
NL_UTILS/py.typed
NL_UTILS/test.py
nlweb_org_utils-0.1.63.dist-info/licenses/LICENSE
src2/aws/ACM.py
src2/aws/ACM_CERTIFICATE.py
src2/aws/ACM_TESTS.py
src2/aws/APIGW.py
src2/aws/APIGW_DOMAIN.py
src2/aws/APIGW_RESTAPI.py
src2/aws/APIGW_RESTAPI_METHOD.py
nlweb_org_utils-0.1.63.dist-info/METADATA
nlweb_org_utils-0.1.63.dist-info/WHEEL
nlweb_org_utils-0.1.63.dist-info/top_level.txt
nlweb_org_utils-0.1.63.dist-info/RECORD
